MQTTLibrary/MQTTKeywords.py
MQTTLibrary/__init__.py
MQTTLibrary/version.py
robotframework_mqtt5library-0.8.3.dist-info/LICENSE.txt
robotframework_mqtt5library-0.8.3.dist-info/METADATA
robotframework_mqtt5library-0.8.3.dist-info/WHEEL
robotframework_mqtt5library-0.8.3.dist-info/top_level.txt
robotframework_mqtt5library-0.8.3.dist-info/RECORD
