Metadata-Version: 2.1
Name: robotframework-mqtt5library
Version: 0.8.3
Summary: MQTT5Library is a Robot Framework library that provides keywords for testing on MQTTv5 brokers.
Author-email: Gaurav Gupta <gaurav@randomsync.net>, Emil Söderberg <emil@stutt.se>
Project-URL: Homepage, https://github.com/kemilsoderberg/robotframework-mqtt5library
Keywords: robotframework,testing,testautomation,mqtt
Classifier: Programming Language :: Python :: 3
Classifier: License :: OSI Approved :: Apache Software License
Classifier: Operating System :: OS Independent
Classifier: Topic :: Software Development :: Testing
Classifier: Development Status :: 3 - Alpha
Requires-Python: >=3.7
License-File: LICENSE.txt
Requires-Dist: paho-mqtt
